{
  "meta": {
    "version": "1.0",
    "generator": "MMOLite Asset Pipeline",
    "sheet_name": "SM_FireWallTorchPot_AM_03_on",
    "max_size": 2048
  },
  "sheets": [
    "SM_FireWallTorchPot_AM_03_on_00.png"
  ],
  "frames": {
    "SM_FireWallTorchPot_AM_03_on_east": {
      "sheet": 0,
      "frame": {
        "x": 0,
        "y": 0,
        "w": 20,
        "h": 56
      },
      "trimmed": true,
      "offset": {
        "x": 63,
        "y": 0
      },
      "source": {
        "w": 128,
        "h": 128
      }
    },
    "SM_FireWallTorchPot_AM_03_on_north": {
      "sheet": 0,
      "frame": {
        "x": 20,
        "y": 0,
        "w": 20,
        "h": 56
      },
      "trimmed": true,
      "offset": {
        "x": 63,
        "y": 0
      },
      "source": {
        "w": 128,
        "h": 128
      }
    },
    "SM_FireWallTorchPot_AM_03_on_south": {
      "sheet": 0,
      "frame": {
        "x": 40,
        "y": 0,
        "w": 20,
        "h": 56
      },
      "trimmed": true,
      "offset": {
        "x": 63,
        "y": 0
      },
      "source": {
        "w": 128,
        "h": 128
      }
    },
    "SM_FireWallTorchPot_AM_03_on_west": {
      "sheet": 0,
      "frame": {
        "x": 60,
        "y": 0,
        "w": 20,
        "h": 56
      },
      "trimmed": true,
      "offset": {
        "x": 63,
        "y": 0
      },
      "source": {
        "w": 128,
        "h": 128
      }
    }
  },
  "animations": {}
}