{
  "meta": {
    "version": "1.0",
    "generator": "MMOLite Asset Pipeline",
    "sheet_name": "SK_Werewolf_Separate2",
    "max_size": 2048
  },
  "sheets": [
    "SK_Werewolf_Separate2_00.png"
  ],
  "frames": {
    "SK_Werewolf_Separate2_east": {
      "sheet": 0,
      "frame": {
        "x": 0,
        "y": 0,
        "w": 46,
        "h": 23
      },
      "trimmed": true,
      "offset": {
        "x": 49,
        "y": 0
      },
      "source": {
        "w": 128,
        "h": 128
      }
    },
    "SK_Werewolf_Separate2_north": {
      "sheet": 0,
      "frame": {
        "x": 46,
        "y": 0,
        "w": 46,
        "h": 23
      },
      "trimmed": true,
      "offset": {
        "x": 49,
        "y": 0
      },
      "source": {
        "w": 128,
        "h": 128
      }
    },
    "SK_Werewolf_Separate2_south": {
      "sheet": 0,
      "frame": {
        "x": 92,
        "y": 0,
        "w": 46,
        "h": 23
      },
      "trimmed": true,
      "offset": {
        "x": 49,
        "y": 0
      },
      "source": {
        "w": 128,
        "h": 128
      }
    },
    "SK_Werewolf_Separate2_west": {
      "sheet": 0,
      "frame": {
        "x": 138,
        "y": 0,
        "w": 46,
        "h": 23
      },
      "trimmed": true,
      "offset": {
        "x": 49,
        "y": 0
      },
      "source": {
        "w": 128,
        "h": 128
      }
    }
  },
  "animations": {}
}