{
  "asset": "SM_Scope_25x56_Y",
  "type": "weapon",
  "frames": {
    "SM_Scope_25x56_Y_south": "F:\\LOVE - Gacha\\MMOLite\\tools\\asset-pipeline\\output/frames\\SM_Scope_25x56_Y\\SM_Scope_25x56_Y_south.png",
    "SM_Scope_25x56_Y_west": "F:\\LOVE - Gacha\\MMOLite\\tools\\asset-pipeline\\output/frames\\SM_Scope_25x56_Y\\SM_Scope_25x56_Y_west.png",
    "SM_Scope_25x56_Y_north": "F:\\LOVE - Gacha\\MMOLite\\tools\\asset-pipeline\\output/frames\\SM_Scope_25x56_Y\\SM_Scope_25x56_Y_north.png",
    "SM_Scope_25x56_Y_east": "F:\\LOVE - Gacha\\MMOLite\\tools\\asset-pipeline\\output/frames\\SM_Scope_25x56_Y\\SM_Scope_25x56_Y_east.png"
  }
}