{
  "meta": {
    "version": "1.0",
    "generator": "MMOLite Asset Pipeline",
    "sheet_name": "SM_BaseBlock_017_on",
    "max_size": 4096
  },
  "sheets": [
    "SM_BaseBlock_017_on_00.png"
  ],
  "frames": {
    "SM_BaseBlock_017_on_east": {
      "sheet": 0,
      "frame": {
        "x": 0,
        "y": 0,
        "w": 232,
        "h": 245
      },
      "trimmed": true,
      "offset": {
        "x": 12,
        "y": 11
      },
      "source": {
        "w": 256,
        "h": 256
      }
    },
    "SM_BaseBlock_017_on_north": {
      "sheet": 0,
      "frame": {
        "x": 232,
        "y": 0,
        "w": 232,
        "h": 245
      },
      "trimmed": true,
      "offset": {
        "x": 12,
        "y": 11
      },
      "source": {
        "w": 256,
        "h": 256
      }
    },
    "SM_BaseBlock_017_on_south": {
      "sheet": 0,
      "frame": {
        "x": 464,
        "y": 0,
        "w": 232,
        "h": 245
      },
      "trimmed": true,
      "offset": {
        "x": 12,
        "y": 11
      },
      "source": {
        "w": 256,
        "h": 256
      }
    },
    "SM_BaseBlock_017_on_west": {
      "sheet": 0,
      "frame": {
        "x": 696,
        "y": 0,
        "w": 232,
        "h": 245
      },
      "trimmed": true,
      "offset": {
        "x": 12,
        "y": 11
      },
      "source": {
        "w": 256,
        "h": 256
      }
    }
  },
  "animations": {}
}